secapi/__init__.py
secapi/client.py
secapi-0.1.0.dist-info/AUTHORS.rst
secapi-0.1.0.dist-info/METADATA
secapi-0.1.0.dist-info/WHEEL
secapi-0.1.0.dist-info/top_level.txt
secapi-0.1.0.dist-info/RECORD
