Metadata-Version: 2.1
Name: secapi
Version: 0.1.0
Summary: A client library for SEC company filings and registration info.
Home-page: https://github.com/sec-api/sec-api-python-client
Author: https://sec-api.com
Author-email: contact@sec-api.com
License: UNKNOWN
Keywords: secapi
Platform: UNKNOWN
Classifier: Development Status :: 2 - Pre-Alpha
Classifier: Intended Audience :: Developers
Classifier: Natural Language :: English
Classifier: Programming Language :: Python :: 3
Classifier: Programming Language :: Python :: 3.5
Classifier: Programming Language :: Python :: 3.6
Classifier: Programming Language :: Python :: 3.7
Classifier: Programming Language :: Python :: 3.8
Requires-Python: >=3.5
